useful_decorators/__init__.py
useful_decorators/functions.py
useful_decorators/patterns.py
useful_decorators-0.0.3.dist-info/LICENSE
useful_decorators-0.0.3.dist-info/WHEEL
useful_decorators-0.0.3.dist-info/METADATA
useful_decorators-0.0.3.dist-info/RECORD
