Metadata-Version: 2.1
Name: useful-decorators
Version: 0.0.3
Summary: Some decorators for Python
Keywords: decorator,python,extensions
Author-email: Jannes Mülller <jannes@mlrjs.de>
Requires-Python: >=3.6
Classifier: Development Status :: 4 - Beta
Classifier: Intended Audience :: Developers
Classifier: License :: OSI Approved :: MIT License
Classifier: Programming Language :: Python :: 3
Classifier: Programming Language :: Python :: 3.6
Classifier: Programming Language :: Python :: 3.7
Classifier: Programming Language :: Python :: 3.8
Classifier: Programming Language :: Python :: 3.9
Classifier: Programming Language :: Python :: 3.10
Classifier: Topic :: Software Development :: Libraries :: Python Modules
Project-URL: changelog, https://github.com/Hypercookie/UsefulDecorators/releases
Project-URL: documentation, https://github.com/Hypercookie/UsefulDecorators
Project-URL: homepage, https://github.com/Hypercookie/UsefulDecorators
